Metadata-Version: 2.1
Name: regeorg
Version: 2.0.1
Summary: pwn a bastion webserver and create SOCKS proxies through the DMZ. Pivot and pwn.
Home-page: https://github.com/kost/regeorg
Author: Vlatko Kosturjak
Author-email: vlatko.kosturjak@gmail.com
License: UNKNOWN
Platform: UNKNOWN
Classifier: Programming Language :: Python :: 2
Classifier: Programming Language :: Python :: 3
Classifier: License :: OSI Approved :: MIT License
Classifier: Operating System :: OS Independent
